nlpaug/__init__.py
nlpaug/base_augmenter.py
nlpaug/augmenter/__init__.py
nlpaug/augmenter/augment.py
nlpaug/augmenter/audio/__init__.py
nlpaug/augmenter/audio/audio_augmenter.py
nlpaug/augmenter/audio/crop.py
nlpaug/augmenter/audio/inversion.py
nlpaug/augmenter/audio/loudness.py
nlpaug/augmenter/audio/mask.py
nlpaug/augmenter/audio/noise.py
nlpaug/augmenter/audio/normalization.py
nlpaug/augmenter/audio/pitch.py
nlpaug/augmenter/audio/shift.py
nlpaug/augmenter/audio/speed.py
nlpaug/augmenter/audio/vtlp.py
nlpaug/augmenter/char/__init__.py
nlpaug/augmenter/char/char_augmenter.py
nlpaug/augmenter/char/keyboard.py
nlpaug/augmenter/char/ocr.py
nlpaug/augmenter/char/random.py
nlpaug/augmenter/sentence/__init__.py
nlpaug/augmenter/sentence/abst_summ.py
nlpaug/augmenter/sentence/context_word_embs_sentence.py
nlpaug/augmenter/sentence/lambada.py
nlpaug/augmenter/sentence/random.py
nlpaug/augmenter/sentence/sentence_augmenter.py
nlpaug/augmenter/spectrogram/__init__.py
nlpaug/augmenter/spectrogram/frequency_masking.py
nlpaug/augmenter/spectrogram/loudness.py
nlpaug/augmenter/spectrogram/spectrogram_augmenter.py
nlpaug/augmenter/spectrogram/time_masking.py
nlpaug/augmenter/spectrogram/time_warping.py
nlpaug/augmenter/word/__init__.py
nlpaug/augmenter/word/antonym.py
nlpaug/augmenter/word/back_translation.py
nlpaug/augmenter/word/context_word_embs.py
nlpaug/augmenter/word/random.py
nlpaug/augmenter/word/reserved.py
nlpaug/augmenter/word/spelling.py
nlpaug/augmenter/word/split.py
nlpaug/augmenter/word/synonym.py
nlpaug/augmenter/word/tfidf.py
nlpaug/augmenter/word/word_augmenter.py
nlpaug/augmenter/word/word_embs.py
nlpaug/flow/__init__.py
nlpaug/flow/pipeline.py
nlpaug/flow/sequential.py
nlpaug/flow/sometimes.py
nlpaug/model/__init__.py
nlpaug/model/base_model.py
nlpaug/model/audio/__init__.py
nlpaug/model/audio/audio.py
nlpaug/model/audio/crop.py
nlpaug/model/audio/inversion.py
nlpaug/model/audio/loudness.py
nlpaug/model/audio/mask.py
nlpaug/model/audio/noise.py
nlpaug-1.1.8.dist-info/LICENSE
nlpaug-1.1.8.dist-info/METADATA
nlpaug-1.1.8.dist-info/WHEEL
nlpaug-1.1.8.dist-info/top_level.txt
nlpaug-1.1.8.dist-info/RECORD
