Metadata-Version: 2.1
Name: nlpaug
Version: 1.1.8
Summary: Natural language processing augmentation library for deep neural networks
Home-page: https://github.com/makcedward/nlpaug
Author: Edward Ma
Author-email: makcedward@gmail.com
License: MIT
Keywords: deep learning,neural network,machine learning,nlp,natural language processing,text,audio,spectrogram,augmentation,adversarial attack,ai,ml
Platform: UNKNOWN
Requires-Dist: numpy (>=1.16.2)
Requires-Dist: pandas (>=1.2.0)
Requires-Dist: requests (>=2.22.0)
